[
  {
    "timestamp": "2025-12-18T07:06:13.875Z",
    "type": "question_for_future",
    "data": {
      "question": "How can I improve the shutdown sequence?"
    }
  },
  {
    "timestamp": "2025-12-18T07:28:26.638Z",
    "type": "question_for_future",
    "data": {
      "question": "How can I improve the shutdown sequence?"
    }
  },
  {
    "timestamp": "2025-12-18T07:31:06.543Z",
    "type": "question_for_future",
    "data": {
      "question": "How can I improve the shutdown sequence?"
    }
  },
  {
    "timestamp": "2025-12-18T22:36:00.851Z",
    "type": "question_for_future",
    "data": {
      "question": "How can I improve the shutdown sequence?"
    }
  }
]